crams_notification/__init__.py
crams_notification/asgi.py
crams_notification/celery.py
crams_notification/settings.py
crams_notification/tasks.py
crams_notification/test_settings.py
crams_notification/urls.py
crams_notification/wsgi.py
crams_notification/mail/__init__.py
crams_notification/mail/mail_sender.py
crams_notification/utils/__init__.py
crams_notification/utils/mail_util.py
crams_notification/views/__init__.py
crams_notification/views/support_email.py
templates/__init__.py
templates/test_tpl/__init__.py
templates/test_tpl/submit.tpl
crams_notification-1.0.0.dist-info/METADATA
crams_notification-1.0.0.dist-info/WHEEL
crams_notification-1.0.0.dist-info/top_level.txt
crams_notification-1.0.0.dist-info/RECORD
