Metadata-Version: 2.1
Name: crams-notification
Version: 1.0.0
Summary: CRAMS API opensource crams notification package.
Home-page: https://github.com/CRAMS-Dashboard/crams-api
Author: Monash University e-Research Centre
Author-email: crams@monash.edu
License: GNU General Public License v3.0
Platform: UNKNOWN
Classifier: Development Status :: 4 - Beta
Classifier: Environment :: Web Environment
Classifier: Intended Audience :: Developers
Classifier: License :: OSI Approved :: GNU General Public License v3 (GPLv3)
Classifier: Operating System :: OS Independent
Classifier: Programming Language :: Python :: 3.8
Classifier: Programming Language :: Python :: 3.9
Classifier: Framework :: Django :: 3.2
Classifier: Topic :: Software Development :: Libraries :: Application Frameworks
Classifier: Topic :: Software Development :: Libraries :: Python Modules
Requires-Python: >=3.8.0
Requires-Dist: merc-common (>=1.0.0)
